FabricFramework/ApiDataSource.py
FabricFramework/DataSource.py
FabricFramework/DataValidation.py
FabricFramework/DeploymentTesting.py
FabricFramework/FabricCache.py
FabricFramework/FabricConfiguration.py
FabricFramework/FabricDataInterface.py
FabricFramework/FabricFramework.py
FabricFramework/FabricLocations.py
FabricFramework/LogMonitor.py
FabricFramework/__init__.py
FabricFramework/ExpectedResults/__init__.py
FabricFramework/ExpectedResults/employees-cdc-delete.csv
FabricFramework/ExpectedResults/employees-cdc-insert.csv
FabricFramework/ExpectedResults/employees-cdc-update.csv
FabricFramework/ExpectedResults/employees-delete.csv
FabricFramework/ExpectedResults/employees-gx-boolean-invalid-rows.csv
FabricFramework/ExpectedResults/employees-gx-double-invalid-rows.csv
FabricFramework/ExpectedResults/employees-gx-inRange-invalid-rows.csv
FabricFramework/ExpectedResults/employees-gx-int-invalid-rows.csv
FabricFramework/ExpectedResults/employees-gx-null-invalid-rows.csv
FabricFramework/ExpectedResults/employees-gx-regex-invalid-rows.csv
FabricFramework/ExpectedResults/employees-gx-valid-rows.csv
FabricFramework/ExpectedResults/employees-insert.csv
FabricFramework/ExpectedResults/employees-update.csv
FabricFramework/ExpectedResults/employees.csv
antaresfabricframeworkbase-1.2.29.dist-info/licenses/LICENSE.txt
antaresfabricframeworkbase-1.2.29.dist-info/METADATA
antaresfabricframeworkbase-1.2.29.dist-info/WHEEL
antaresfabricframeworkbase-1.2.29.dist-info/top_level.txt
antaresfabricframeworkbase-1.2.29.dist-info/RECORD
