Metadata-Version: 2.4
Name: AntaresFabricFrameworkBase
Version: 1.2.29
Summary: Microsoft Fabric data ingestion accelerator
Home-page: https://antares.solutions/
Author: Antares Solutions
Author-email: yeshanh@antaressolutions.com.au
Project-URL: Bug Tracker, https://antares.solutions/
Classifier: Programming Language :: Python :: 3
Classifier: License :: OSI Approved :: MIT License
Classifier: Operating System :: OS Independent
Requires-Python: >=3.6
License-File: LICENSE.txt
Dynamic: author
Dynamic: author-email
Dynamic: classifier
Dynamic: description
Dynamic: description-content-type
Dynamic: home-page
Dynamic: license-file
Dynamic: project-url
Dynamic: requires-python
Dynamic: summary
